BitStuffErrorBock/BitStuffErrorBock.v
module BitStuffErrorBock( 
input reset, SP, RX, F_STF,
output reg STF_ERR);
	
	reg [7:0] estado_atual;
	reg previous_bit;
	reg [8:0] cont = 0 ;
	reg [8:0] i = 0 ;
	parameter sts1 = 0;
	parameter sts2 = 1;
	
	initial STF_ERR = 1'b1;
	initial previous_bit = ~RX;
	
	always@(posedge SP or posedge reset) begin
		i <= i + 9'd1;
		$display(" ");
		$display("Always entry %d", i);
		$display("Sample point %d", SP);
		$display("Estado %d", estado_atual);
		$display("Contador %d", cont);
		$display("Previous bit %d", previous_bit);
		$display(" ");
		
		if(reset == 1) begin
			estado_atual <= sts1;
			STF_ERR <= 1'b1;
		end
		
		case(estado_atual)
			sts1: begin		//WAITING FOR STUFF
				STF_ERR <= 1'b1;
				if(F_STF == 1'b0) begin
					estado_atual <= sts2;
					cont <= 9'd0;
				end
			end
			sts2: begin		//stuff area
				if(F_STF == 1'b1) begin
					estado_atual <= sts1;
					cont <= 9'd0;
				end
				else begin
					if(previous_bit == RX && cont == 4)begin
						STF_ERR <= 1'b0;
						cont <= 9'd0;
						estado_atual <= sts1;
						$display("Erro de bit Stuff");
					end
					else begin
						if(previous_bit != RX) begin
							cont <= 9'd0;
						end
						else begin
							if(previous_bit == RX && cont<4) begin
								cont <= cont + 9'd1;
							end
						end
					end
				end
				previous_bit <= RX;
			end
		endcase
	end	
endmodule

BitStuffErrorBock/bitStuff_TB.v
//`timescale 1ns/1ps
module bitStuff_TB;

	reg reset, SP, RX, F_STF;
	wire STF_ERR;

BitStuffErrorBock block (reset, SP, RX, F_STF, STF_ERR);

	initial 
	SP = 0;
	
	always
	#3 SP = ~SP;

	initial begin
	
		RX = 0 ; F_STF = 0; reset = 1; # 10;
		RX = 0 ; F_STF = 0; reset = 0; # 10;
		RX = 0 ; F_STF = 0; reset = 0; # 10; //esse bit
		RX = 0 ; F_STF = 0; reset = 0; # 10;
		RX = 1 ; F_STF = 0; reset = 0; # 10; //esse bit
		RX = 1 ; F_STF = 0; reset = 0; # 10;
		RX = 1 ; F_STF = 0; reset = 0; # 10; //esse bit
		RX = 0 ; F_STF = 0; reset = 0; # 10;
		RX = 0 ; F_STF = 0; reset = 0; # 10; //esse bit
		RX = 0 ; F_STF = 0; reset = 0; # 10;
		RX = 1 ; F_STF = 0; reset = 0; # 10; //esse bit
		RX = 1 ; F_STF = 0; reset = 0; # 10;
		RX = 1 ; F_STF = 0; reset = 0; # 10; //esse bit
		RX = 0 ; F_STF = 0; reset = 0; # 10;
		RX = 0 ; F_STF = 0; reset = 0; # 10;
		RX = 0 ; F_STF = 0; reset = 0; # 10; //esse bit
		RX = 0 ; F_STF = 0; reset = 0; # 10; //esse bit
		
		$stop;
	
	end
endmodule

BitStuffErrorBock/simulation/modelsim/BSE.vcd
$date
	Thu Nov 09 00:24:11 2017
$end
$version
	ModelSim Version 10.5b
$end
$timescale
	1ps
$end

$scope module bitStuff_TB $end
$var reg 1 ! reset $end
$var reg 1 " SP $end
$var reg 1 # RX $end
$var reg 1 $ F_STF $end
$var wire 1 % STF_ERR $end

$scope module block $end
$var parameter 32 & sts1 $end
$var parameter 32 ' sts2 $end
$var wire 1 ( reset $end
$var wire 1 ) SP $end
$var wire 1 * RX $end
$var wire 1 + F_STF $end
$var reg 1 , STF_ERR $end
$var reg 8 - estado_atual [7:0] $end
$var reg 1 . previous_bit $end
$var reg 9 / cont [8:0] $end
$var reg 9 0 i [8:0] $end
$upscope $end
$upscope $end
$enddefinitions $end
#0
$dumpvars
1!
0"
0#
0$
1,
b0 -
x.
b0 /
b1 0
b0 &
b1 '
1%
0+
0*
0)
1(
$end
#10
1"
0!
1)
0(
b10 0
b1 -
#20
0"
0)
#30
1"
1)
b11 0
0.
#40
0"
0)
#50
1"
1)
b100 0
b1 /
#60
0"
0)
#70
1"
1)
b101 0
b10 /
#80
0"
0)
#90
1"
1)
b110 0
b11 /
#100
0"
0)
#110
1"
1#
1*
1)
b111 0
b0 /
1.
#120
0"
0#
0*
0)
#130
1"
1)
b1000 0
0.
#140
0"
0)
#150
1"
1)
b1001 0
b1 /
