EOF_Error_Block/EOF_Error_Block.v
//EOF ERROR BLOCK

module EOF_Error_Block(
	
	input reset, SP, RX, EOF_Flag,
   output reg [1:0] EOF_Error
   
	);

reg [7:0]estado_atual;
reg [8:0]cont;
reg [8:0] i = 0 ;

parameter sts1 = 0;
parameter sts2 = 1;
parameter sts3 = 2;



initial cont = 9'd0;
initial EOF_Error = 1'b1;

always@(posedge SP or posedge reset)begin
	if (reset) begin
        estado_atual <= sts1;
        EOF_Error <= 1'b1;
		  cont <= 9'd0;
   end
	
  	case(estado_atual)
      sts1: begin			//Waiting for EOF area
			EOF_Error <= 1'b1; 
			$display("Esperando flag ativar");
			if(EOF_Flag == 1'b0)begin  //Se a FLAG estiver em 0, já estamos no primeiro bit do EOF!!!
				$display("Flag ativada");
				estado_atual <= sts2;
				cont <= 9'd0;
				if(RX == 0)begin 		//EOF Error found
					$display("Erro encontrado");
					EOF_Error <= 1'b0;
					cont <= 9'd0;
					estado_atual <= sts1;
          	end
			end
      end
      sts2: begin  	//EOF Area SEGUNDO BIT
			if(cont == 5) begin
				$display("Tudo certo");
				cont <= 9'd0;
				estado_atual <= sts3;
			end
			if(RX == 0 && cont < 5)begin //EOF Error found
				$display("Erro encontrado");
				EOF_Error <= 1'b0;
            cont <= 9'd0;
            estado_atual <= sts1;
			end
			else begin
				cont <= cont + 9'd1;
			end
      end
      sts3: begin //EOF LAST BIT
			$display("Voltando a esperar flag ativar");
			estado_atual <= sts1;
      end
   endcase
end
endmodule

EOF_Error_Block/EOF_Error_Block_TB.v
//`timescale 1ns/1ps
module EOF_Error_Block_TB;

	reg reset, SP, RX, EOF_Flag;
	wire EOF_Error;

EOF_Error_Block block (reset, SP, RX, EOF_Flag, EOF_Error);

	initial begin
	
		//TUDO CERTO
		SP = 0; RX = 0 ; EOF_Flag = 1; reset = 1; # 10;
		SP = 1; RX = 1 ; EOF_Flag = 0; reset = 0; # 10; //esse bit
		SP = 0; RX = 0 ; EOF_Flag = 0; reset = 0; # 10;
		SP = 1; RX = 1 ; EOF_Flag = 0; reset = 0; # 10; //esse bit
		SP = 0; RX = 0 ; EOF_Flag = 0; reset = 0; # 10;
		SP = 1; RX = 1 ; EOF_Flag = 0; reset = 0; # 10; //esse bit
		SP = 0; RX = 0 ; EOF_Flag = 0; reset = 0; # 10;
		SP = 1; RX = 1 ; EOF_Flag = 0; reset = 0; # 10; //esse bit
		SP = 0; RX = 0 ; EOF_Flag = 0; reset = 0; # 10;
		SP = 1; RX = 1 ; EOF_Flag = 0; reset = 0; # 10; //esse bit
		SP = 0; RX = 0 ; EOF_Flag = 0; reset = 0; # 10;
		SP = 1; RX = 1 ; EOF_Flag = 0; reset = 0; # 10; //esse bit
		SP = 0; RX = 0 ; EOF_Flag = 0; reset = 0; # 10;
		SP = 1; RX = 1 ; EOF_Flag = 0; reset = 0; # 10; //esse bit
		SP = 0; RX = 0 ; EOF_Flag = 1; reset = 0; # 10;
		SP = 1; RX = 0 ; EOF_Flag = 1; reset = 0; # 10; //esse bit
		
	
		//BIT DOMINANTE NO EOF
		SP = 0; RX = 0 ; EOF_Flag = 1; reset = 0; # 10; 
		SP = 1; RX = 1 ; EOF_Flag = 0; reset = 0; # 10; //esse bit
		SP = 0; RX = 0 ; EOF_Flag = 0; reset = 0; # 10;
		SP = 1; RX = 1 ; EOF_Flag = 0; reset = 0; # 10; //esse bit
		SP = 0; RX = 0 ; EOF_Flag = 0; reset = 0; # 10;
		SP = 1; RX = 1 ; EOF_Flag = 0; reset = 0; # 10; //esse bit
		SP = 0; RX = 0 ; EOF_Flag = 0; reset = 0; # 10;
		SP = 1; RX = 0 ; EOF_Flag = 0; reset = 0; # 10; //esse bit
		SP = 0; RX = 0 ; EOF_Flag = 0; reset = 0; # 10;
		SP = 1; RX = 1 ; EOF_Flag = 0; reset = 0; # 10; //esse bit
		SP = 0; RX = 0 ; EOF_Flag = 0; reset = 0; # 10;
		SP = 1; RX = 1 ; EOF_Flag = 0; reset = 0; # 10; //esse bit
		SP = 0; RX = 0 ; EOF_Flag = 0; reset = 0; # 10;
		SP = 1; RX = 1 ; EOF_Flag = 0; reset = 0; # 10; //esse bit
		
		//BIT DOMINANTE NO ULTIMO BIT DO EOF
		SP = 0; RX = 0 ; EOF_Flag = 1; reset = 0; # 10;
		SP = 1; RX = 1 ; EOF_Flag = 0; reset = 0; # 10; //esse bit
		SP = 0; RX = 0 ; EOF_Flag = 0; reset = 0; # 10;
		SP = 1; RX = 1 ; EOF_Flag = 0; reset = 0; # 10; //esse bit
		SP = 0; RX = 0 ; EOF_Flag = 0; reset = 0; # 10;
		SP = 1; RX = 1 ; EOF_Flag = 0; reset = 0; # 10; //esse bit
		SP = 0; RX = 0 ; EOF_Flag = 0; reset = 0; # 10;
		SP = 1; RX = 0 ; EOF_Flag = 0; reset = 0; # 10; //esse bit
		SP = 0; RX = 0 ; EOF_Flag = 0; reset = 0; # 10;
		SP = 1; RX = 1 ; EOF_Flag = 0; reset = 0; # 10; //esse bit
		SP = 0; RX = 0 ; EOF_Flag = 0; reset = 0; # 10;
		SP = 1; RX = 1 ; EOF_Flag = 0; reset = 0; # 10; //esse bit
		SP = 0; RX = 0 ; EOF_Flag = 0; reset = 0; # 10;
		SP = 1; RX = 0 ; EOF_Flag = 0; reset = 0; # 10; //esse bit
		
		//BIT DOMINANTE NO PRIMEIRO BIT DO EOF
		SP = 0; RX = 0 ; EOF_Flag = 1; reset = 0; # 10;
		SP = 1; RX = 0 ; EOF_Flag = 0; reset = 0; # 10; //esse bit
		SP = 0; RX = 0 ; EOF_Flag = 0; reset = 0; # 10;
		SP = 1; RX = 1 ; EOF_Flag = 0; reset = 0; # 10; //esse bit
		SP = 0; RX = 0 ; EOF_Flag = 0; reset = 0; # 10;
		SP = 1; RX = 1 ; EOF_Flag = 0; reset = 0; # 10; //esse bit
		SP = 0; RX = 0 ; EOF_Flag = 0; reset = 0; # 10;
		SP = 1; RX = 0 ; EOF_Flag = 0; reset = 0; # 10; //esse bit
		SP = 0; RX = 0 ; EOF_Flag = 0; reset = 0; # 10;
		SP = 1; RX = 1 ; EOF_Flag = 0; reset = 0; # 10; //esse bit
		SP = 0; RX = 0 ; EOF_Flag = 0; reset = 0; # 10;
		SP = 1; RX = 1 ; EOF_Flag = 0; reset = 0; # 10; //esse bit
		SP = 0; RX = 0 ; EOF_Flag = 0; reset = 0; # 10;
		SP = 1; RX = 1 ; EOF_Flag = 0; reset = 0; # 10; //esse bit
		
		//TUDO CERTO AGAIN
		SP = 0; RX = 0 ; EOF_Flag = 1; reset = 0; # 10; 
		SP = 1; RX = 1 ; EOF_Flag = 0; reset = 0; # 10; //esse bit
		SP = 0; RX = 0 ; EOF_Flag = 0; reset = 0; # 10;
		SP = 1; RX = 1 ; EOF_Flag = 0; reset = 0; # 10; //esse bit
		SP = 0; RX = 0 ; EOF_Flag = 0; reset = 0; # 10;
		SP = 1; RX = 1 ; EOF_Flag = 0; reset = 0; # 10; //esse bit
		SP = 0; RX = 0 ; EOF_Flag = 0; reset = 0; # 10;
		SP = 1; RX = 1 ; EOF_Flag = 0; reset = 0; # 10; //esse bit
		SP = 0; RX = 0 ; EOF_Flag = 0; reset = 0; # 10;
		SP = 1; RX = 1 ; EOF_Flag = 0; reset = 0; # 10; //esse bit
		SP = 0; RX = 0 ; EOF_Flag = 0; reset = 0; # 10;
		SP = 1; RX = 1 ; EOF_Flag = 0; reset = 0; # 10; //esse bit
		SP = 0; RX = 0 ; EOF_Flag = 0; reset = 0; # 10;
		SP = 1; RX = 1 ; EOF_Flag = 0; reset = 0; # 10; //esse bit
		SP = 0; RX = 0 ; EOF_Flag = 1; reset = 0; # 10;
		SP = 1; RX = 0 ; EOF_Flag = 1; reset = 0; # 10; //esse bit
		
		
		$display("");
	
	end
endmodule

FRAME MAKER/ERROR BLOCK/EOF Error Block/simulation/modelsim/BSE.vcd
$date
	Sat Nov 11 14:56:11 2017
$end
$version
	ModelSim Version 10.5b
$end
$timescale
	1ps
$end

$scope module EOF_Error_Block_TB $end
$var reg 1 ! reset $end
$var reg 1 " SP $end
$var reg 1 # RX $end
$var reg 1 $ EOF_Flag $end
$var wire 1 % EOF_Error $end

$scope module block $end
$var parameter 32 & sts1 $end
$var parameter 32 ' sts2 $end
$var parameter 32 ( sts3 $end
$var wire 1 ) reset $end
$var wire 1 * SP $end
$var wire 1 + RX $end
$var wire 1 , EOF_Flag $end
$var reg 2 - EOF_Error [1:0] $end
$var reg 8 . estado_atual [7:0] $end
$var reg 9 / cont [8:0] $end
$var reg 9 0 i [8:0] $end
$upscope $end
$upscope $end
$enddefinitions $end
#0
$dumpvars
1!
0"
0#
1$
b1 -
b0 .
b0 /
b1 0
b0 &
b1 '
b10 (
1%
1,
0+
0*
1)
$end
#10
1"
1#
0$
0!
1+
0,
1*
0)
b10 0
b1 .
#20
0"
0#
0+
0*
#30
1"
1#
1+
1*
b11 0
b1 /
#40
0"
0#
0+
0*
#50
1"
1#
1+
1*
b100 0
b10 /
#60
0"
0#
0+
0*
#70
1"
1#
1+
1*
b101 0
b11 /
#80
0"
0#
0+
0*
#90
1"
1#
1+
1*
b110 0
b100 /
#100
0"
0#
0+
0*
#110
1"
1#
1+
1*
b111 0
b101 /
#120
0"
0#
0+
0*
#130
1"
1#
1+
1*
b1000 0
b10 .
b0 /
b110 /
#140
0"
0#
1$
0+
1,
0*
#150
1"
1*
b1001 0
b0 .
#160
0"
0*
#170
1"
1#
0$
1+
0,
1*
b1010 0
b1 .
b0 /
#180
0"
0#
0+
0*
#190
1"
1#
1+
1*
b1011 0
b1 /
#200
0"
0#
0+
0*
#210
1"
1#
1+
1*
b1100 0
b10 /
#220
0"
0#
0+
0*
#230
1"
1*
b1101 0
b0 -
b0 /
b0 .
0%
#240
0"
0*
#250
1"
1#
1+
1*
b1110 0
b1 -
b1 .
1%
#260
0"
0#
0+
0*
#270
1"
1#
1+
1*
b1111 0
b1 /
#280
0"
0#
0+
0*
#290
1"
1#
1+
1*
b10000 0
b10 /
#300
0"
0#
1$
0+
1,
0*
#310
1"
1#
0$
1+
0,
1*
b10001 0
b11 /
#320
0"
0#
0+
0*
#330
1"
1#
1+
1*
b10010 0
b100 /
#340
0"
0#
0+
0*
#350
1"
1#
1+
1*
b10011 0
b101 /
#360
0"
0#
0+
0*
#370
1"
1*
b10100 0
b10 .
b0 /
b0 -
b0 .
0%
#380
0"
0*
#390
1"
1#
1+
1*
b10101 0
b1 -
b1 .
1%
#400
0"
0#
0+
0*
#410
1"
1#
1+
1*
b10110 0
b1 /
#420
0"
0#
0+
0*
#430
1"
1*
b10111 0
b0 -
b0 /
b0 .
0%
#440
0"
1$
1,
0*
#450
1"
0$
0,
1*
b11000 0
b1 -
b1 .
b0 -
b0 .
#460
0"
0*
#470
1"
1#
1+
1*
b11001 0
b1 -
b1 .
1%
#480
0"
0#
0+
0*
#490
1"
1#
1+
1*
b11010 0
b1 /
#500
0"
0#
0+
0*
#510
1"
1*
b11011 0
b0 -
b0 /
b0 .
0%
#520
0"
0*
#530
1"
1#
1+
1*
b11100 0
b1 -
b1 .
1%
#540
0"
0#
0+
0*
#550
1"
1#
1+
1*
b11101 0
b1 /
#560
0"
0#
0+
0*
#570
1"
1#
1+
1*
b11110 0
b10 /
#580
0"
0#
1$
0+
1,
0*
#590
1"
1#
0$
1+
0,
1*
b11111 0
b11 /
#600
0"
0#
0+
0*
#610
1"
1#
1+
1*
b100000 0
b100 /
#620
0"
0#
0+
0*
#630
1"
1#
1+
1*
b100001 0
b101 /
#640
0"
0#
0+
0*
#650
1"
1#
1+
1*
b100010 0
b10 .
b0 /
b110 /
#660
0"
0#
0+
0*
#670
1"
1#
1+
1*
b100011 0
b0 .
#680
0"
0#
0+
0*
#690
1"
1#
1+
1*
b100100 0
b1 .
b0 /
#700
0"
0#
0+
0*
#710
1"
1#
1+
1*
b100101 0
b1 /
#720
0"
0#
1$
0+
1,
0*
#730
1"
1*
b100110 0
b0 -
b0 /
b0 .
0%
